Metadata-Version: 1.1
Name: brokkoly
Version: 0.3.1
Summary: Brokkoly is a framework for enqueuing messages via HTTP request for celery.
Home-page: https://github.com/narusemotoki/brokkoly
Author: Motoki Naruse
Author-email: motoki@naru.se
License: MIT
Keywords: celery,queue
Platform: UNKNOWN
Classifier: Development Status :: 1 - Planning
Classifier: Intended Audience :: Developers
Classifier: License :: OSI Approved :: MIT License
Classifier: Programming Language :: Python :: 3
Classifier: Programming Language :: Python :: 3.4
Classifier: Programming Language :: Python :: 3.5
Classifier: Programming Language :: Python :: 3.6
Classifier: Programming Language :: Python :: 3 :: Only
Classifier: Topic :: Software Development :: Libraries
